{
    "compatible_printers": [
        "Creality Hi 0.4 nozzle"
    ],
    "enable_pressure_advance": [
        "1"
    ],
    "fan_cooling_layer_time": [
        "30"
    ],
    "fan_max_speed": [
        "50"
    ],
    "filament_flow_ratio": [
        "0.93"
    ],
    "filament_retraction_length": [
        "1"
    ],
    "filament_settings_id": [
        "PETG-GF(Creality Hi-Orca-TINMORRY)"
    ],
    "filament_z_hop_types": [
        "Spiral Lift"
    ],
    "from": "User",
    "inherits": "Generic PETG @System",
    "is_custom_defined": "0",
    "name": "PETG-GF(Creality Hi-Orca-TINMORRY)",
    "nozzle_temperature": [
        "260"
    ],
    "nozzle_temperature_initial_layer": [
        "260"
    ],
    "nozzle_temperature_range_high": [
        "270"
    ],
    "nozzle_temperature_range_low": [
        "250"
    ],
    "pressure_advance": [
        "0.035"
    ],
    "slow_down_layer_time": [
        "12"
    ],
    "version": "2.3.0.3"
}
